pep440_rs-0.6.5.dist-info/METADATA
pep440_rs-0.6.5.dist-info/WHEEL
pep440_rs.libs/libgcc_s-b5472b99.so.1
pep440_rs/__init__.pyi
pep440_rs/__init__.py
pep440_rs/_pep440_rs.abi3.so
pep440_rs-0.6.5.dist-info/RECORD
