Metadata-Version: 2.3
Name: pep440_rs
Version: 0.6.5
Summary: A library for python version numbers and specifiers, implementing PEP 440
License: Apache-2.0 OR BSD-2-Clause
Project-URL: Source Code, https://github.com/konstin/pep440-rs
